main.py
testing_rag-0.0.2.dist-info/METADATA
testing_rag-0.0.2.dist-info/WHEEL
testing_rag-0.0.2.dist-info/top_level.txt
testing_rag-0.0.2.dist-info/RECORD
