Metadata-Version: 2.1
Name: testing-rag
Version: 0.0.2
Summary: rag backend package
Author-email: tlabs <shubham.s@antino.com>
Project-URL: Homepage, https://github.com/pypa/rag-be
Project-URL: Issues, https://github.com/pypa/rag-be/issues
Classifier: Programming Language :: Python :: 3
Classifier: License :: OSI Approved :: MIT License
Classifier: Operating System :: OS Independent
Requires-Python: >=3.8
